alga/__init__.py
alga/__main__.py
alga/cli_adhoc.py
alga/cli_app.py
alga/cli_channel.py
alga/cli_input.py
alga/cli_media.py
alga/cli_power.py
alga/cli_remote.py
alga/cli_sound_output.py
alga/cli_tv.py
alga/cli_version.py
alga/cli_volume.py
alga/client.py
alga/config.py
alga/payloads.py
alga/py.typed
alga/types.py
alga-2.2.0.dist-info/METADATA
alga-2.2.0.dist-info/WHEEL
alga-2.2.0.dist-info/entry_points.txt
alga-2.2.0.dist-info/licenses/LICENSE
alga-2.2.0.dist-info/RECORD
