Metadata-Version: 2.4
Name: alga
Version: 2.2.0
Summary: CLI for remote controlling LG webOS TVs
Project-URL: documentation, https://github.com/Tenzer/alga/blob/main/usage.md
Project-URL: homepage, https://github.com/Tenzer/alga
Project-URL: issues, https://github.com/Tenzer/alga/issues
Project-URL: releasenotes, https://github.com/Tenzer/alga/releases
Project-URL: source, https://github.com/Tenzer/alga.git
Author-email: Jeppe Fihl-Pearson <jeppe@tenzer.dk>
License-Expression: MIT
License-File: LICENSE
Keywords: lg,lgtv,remote,remote-control,webos,webos-tv
Classifier: Development Status :: 5 - Production/Stable
Classifier: Environment :: Console
Classifier: Intended Audience :: End Users/Desktop
Classifier: License :: OSI Approved :: MIT License
Classifier: Natural Language :: English
Classifier: Operating System :: OS Independent
Classifier: Programming Language :: Python :: 3.10
Classifier: Programming Language :: Python :: 3.11
Classifier: Programming Language :: Python :: 3.12
Classifier: Programming Language :: Python :: 3.13
Classifier: Programming Language :: Python :: 3.14
Classifier: Programming Language :: Python :: 3.15
Classifier: Topic :: Home Automation
Classifier: Topic :: Multimedia
Classifier: Typing :: Typed
Requires-Python: >=3.10
Requires-Dist: cfgs>=0.13.0
Requires-Dist: getmac>=0.9.0
Requires-Dist: pzp>=0.0.25
Requires-Dist: rich>=13.0.0
Requires-Dist: typer>=0.15.4
Requires-Dist: wakeonlan>=2.0.0
Requires-Dist: websocket-client>=1.0.0
